{
  "project_info": {
    "project_number": "139098836082",
    "project_id": "rollbrett-rottweil-flutter",
    "storage_bucket": "rollbrett-rottweil-flutter.appspot.com"
  },
  "client": [
    {
      "client_info": {
        "mobilesdk_app_id": "1:139098836082:android:02f623421a230d13c446eb",
        "android_client_info": {
          "package_name": "com.example.rollbrett_rottweil"
        }
      },
      "oauth_client": [
        {
          "client_id": "139098836082-70kn7ag4gs192utl2p442bi49j9jrprk.apps.googleusercontent.com",
          "client_type": 3
        }
      ],
      "api_key": [
        {
          "current_key": "AIzaSyDRdvroDx2IPQXE-gZBnaPO22vylpPszkw"
        }
      ],
      "services": {
        "appinvite_service": {
          "other_platform_oauth_client": [
            {
              "client_id": "139098836082-70kn7ag4gs192utl2p442bi49j9jrprk.apps.googleusercontent.com",
              "client_type": 3
            }
          ]
        }
      }
    }
  ],
  "configuration_version": "1"
}